ai_translator-0.1.0.dist-info/licenses/LICENSE
translator/__init__.py
translator/translator.py
ai_translator-0.1.0.dist-info/METADATA
ai_translator-0.1.0.dist-info/WHEEL
ai_translator-0.1.0.dist-info/top_level.txt
ai_translator-0.1.0.dist-info/RECORD
